yuantool/__init__.py
yuantool/asn1.py
yuantool/common.py
yuantool/coro.py
yuantool/crypto.py
yuantool/decotator.py
yuantool/difinition.py
yuantool/enums.py
yuantool/execute.py
yuantool/file.py
yuantool/path.py
yuantool/time.py
yuantool/unique_queue.py
yuantool/upload.py
yuantool/xmltools.py
yuantool/database/__init__.py
yuantool/database/es_obj.py
yuantool/database/kafka_obj.py
yuantool/database/mongodb_obj.py
yuantool/database/mq_obj.py
yuantool/database/mysql_obj.py
yuantool/database/rabbitmq_obj.py
yuantool/database/redis_obj.py
yuantool/database/sqlite_obj.py
yuantool/fingerprint/__init__.py
yuantool/fingerprint/dataset.feather
yuantool/fingerprint/dataset_creation.py
yuantool/fingerprint/nmap_db_parser.py
yuantool/fingerprint/nmap_db_parser_responses_format.py
yuantool/fingerprint/os-classes-db79-IN.txt
yuantool/fingerprint/__pycache__/__init__.cpython-39.pyc
yuantool/fingerprint/__pycache__/dataset_creation.cpython-39.pyc
yuantool/fingerprint/__pycache__/nmap_db_parser.cpython-39.pyc
yuantool/fingerprint/__pycache__/nmap_db_parser_responses_format.cpython-39.pyc
yuantool/network/__init__.py
yuantool/network/html.py
yuantool/network/ip.py
yuantool/network/port.py
yuantool/network/push.py
yuantool/network/url.py
yuan_tool-2.60.dist-info/METADATA
yuan_tool-2.60.dist-info/WHEEL
yuan_tool-2.60.dist-info/top_level.txt
yuan_tool-2.60.dist-info/RECORD
