Metadata-Version: 2.1
Name: yuan-tool
Version: 2.60
Summary: some common components for personal use
Home-page: 
Author: narukami_yume
Author-email: 100961220@qq.com
Keywords: pip
Platform: any
Requires-Python: >=3.6
Requires-Dist: requests >=2.25
Requires-Dist: lxml >=4.5.2
Requires-Dist: IPy >=1.01
Requires-Dist: PyYAML >=5.4.1
Requires-Dist: paramiko
Requires-Dist: colorama
Requires-Dist: pycryptodome
Requires-Dist: ruamel.yaml
Requires-Dist: redis
Requires-Dist: pymongo
Requires-Dist: pymysql
Requires-Dist: kafka-python
Requires-Dist: elasticsearch ==7.16
Requires-Dist: DBUtils
Requires-Dist: pyDes
Requires-Dist: Crypto
Requires-Dist: dnspython
Requires-Dist: tld
Requires-Dist: psutil
Requires-Dist: cchardet
Requires-Dist: pika
